dumptool/__init__.py
dumptool/introspector.py
dumptool-0.0.1.dist-info/LICENSE.txt
dumptool-0.0.1.dist-info/METADATA
dumptool-0.0.1.dist-info/WHEEL
dumptool-0.0.1.dist-info/top_level.txt
dumptool-0.0.1.dist-info/RECORD
